diagnostics_endpoint/__init__.py
diagnostics_endpoint/diagnostics.py
diagnostics_endpoint/test.py
diagnostics_endpoint/templates/diagnostics.html
diagnostics_endpoint-0.0.8.dist-info/METADATA
diagnostics_endpoint-0.0.8.dist-info/WHEEL
diagnostics_endpoint-0.0.8.dist-info/top_level.txt
diagnostics_endpoint-0.0.8.dist-info/RECORD
