Metadata-Version: 2.1
Name: diagnostics-endpoint
Version: 0.0.8
Summary: Python package fo generating diagnostic endpoint for flask based python web applications.
Home-page: https://github.com/shardulsrivastava/python-diagnostics
Author: Shardul Srivastava
Author-email: shardul.srivastava007@gmail.com
License: MIT
Download-URL: https://pypi.org/project/diagnostics-endpoint/
Keywords: Flask,Endpoint,Diagnostics
Platform: UNKNOWN
Requires-Dist: flask
Requires-Dist: requests
Requires-Dist: jinja2
